{
  "territory": "itapua_py",
  "province": {
    "total_hexes": 68737,
    "avg_score": 34.2,
    "unassigned": 68734
  },
  "departments": [
    {
      "distrito": "San Rafael Del Parana",
      "parquetKey": "san_rafael_del_parana",
      "avg_score": 53.1,
      "hex_count": 2,
      "centroid": [
        -54.8272,
        -26.6491
      ]
    },
    {
      "distrito": "Bella Vista",
      "parquetKey": "bella_vista",
      "avg_score": 47.6,
      "hex_count": 1,
      "centroid": [
        -55.4507,
        -27.036
      ]
    }
  ]
}